pm4mkb/__init__.py
pm4mkb/_cpu_jobs_manager.py
pm4mkb/_logging_init.py
pm4mkb/_version.py
pm4mkb/autoinsights/__init__.py
pm4mkb/autoinsights/_auto_insights.py
pm4mkb/autoinsights/_initialized_metrics.py
pm4mkb/autoinsights/metrics/__init__.py
pm4mkb/autoinsights/metrics/_annotations.py
pm4mkb/autoinsights/metrics/_base.py
pm4mkb/autoinsights/metrics/_failure_return.py
pm4mkb/autoinsights/metrics/_failure_structure.py
pm4mkb/autoinsights/metrics/_frequency_full_loop.py
pm4mkb/autoinsights/metrics/_frequency_irregular.py
pm4mkb/autoinsights/metrics/_frequency_loop.py
pm4mkb/autoinsights/metrics/_frequency_ping_pong.py
pm4mkb/autoinsights/metrics/_frequency_start_loop.py
pm4mkb/autoinsights/metrics/_graph_embedings.py
pm4mkb/autoinsights/metrics/_influencing_activities.py
pm4mkb/autoinsights/metrics/_operation_bottleneck.py
pm4mkb/autoinsights/metrics/_operation_increasing_duration.py
pm4mkb/autoinsights/metrics/_operation_one_incidents.py
pm4mkb/autoinsights/metrics/_process_mistake.py
pm4mkb/autoinsights/metrics/_process_multi_incidents.py
pm4mkb/autoinsights/metrics/catboost_model.dump
pm4mkb/autoinsights/metrics/node2vec.py
pm4mkb/autoinsights/metrics/models/catboost_model.dump
pm4mkb/autoinsights/text_data/__init__.py
pm4mkb/autoinsights/text_data/_text_data_funcs.py
pm4mkb/autoinsights/text_data/mistakes.txt
pm4mkb/autoinsights/text_data/reversal.txt
pm4mkb/batch_analysis/__init__.py
pm4mkb/baza/__init__.py
pm4mkb/baza/_annotations.py
pm4mkb/baza/_data_processing.py
pm4mkb/baza/_datetime_conversion.py
pm4mkb/baza/_sota_utils.py
pm4mkb/baza/_unification.py
pm4mkb/baza/holder.py
pm4mkb/baza/managers/__init__.py
pm4mkb/baza/managers/calendar.py
pm4mkb/baza/managers/data_type.py
pm4mkb/baza/managers/datetime.py
pm4mkb/baza/managers/duration.py
pm4mkb/baza/managers/sorting.py
pm4mkb/baza/managers/success.py
pm4mkb/bpmn/__init__.py
pm4mkb/bpmn/_bpmn_file_to_graph.py
pm4mkb/bpmn/_bpmn_graph_to_file/__init__.py
pm4mkb/bpmn/_bpmn_graph_to_file/_bpmn_exporter.py
pm4mkb-0.1.4.dist-info/LICENSE
pm4mkb-0.1.4.dist-info/METADATA
pm4mkb-0.1.4.dist-info/WHEEL
pm4mkb-0.1.4.dist-info/top_level.txt
pm4mkb-0.1.4.dist-info/RECORD
